odoo/addons/l10n_es_aeat_sii_oss/README.rst
odoo/addons/l10n_es_aeat_sii_oss/__init__.py
odoo/addons/l10n_es_aeat_sii_oss/__manifest__.py
odoo/addons/l10n_es_aeat_sii_oss/data/aeat_sii_mapping_registration_keys_data.xml
odoo/addons/l10n_es_aeat_sii_oss/i18n/l10n_es_aeat_sii_oss.pot
odoo/addons/l10n_es_aeat_sii_oss/models/__init__.py
odoo/addons/l10n_es_aeat_sii_oss/models/account_move.py
odoo/addons/l10n_es_aeat_sii_oss/readme/CONFIGURE.rst
odoo/addons/l10n_es_aeat_sii_oss/readme/CONTRIBUTORS.rst
odoo/addons/l10n_es_aeat_sii_oss/readme/DESCRIPTION.rst
odoo/addons/l10n_es_aeat_sii_oss/readme/INSTALL.rst
odoo/addons/l10n_es_aeat_sii_oss/static/description/icon.png
odoo/addons/l10n_es_aeat_sii_oss/static/description/icon_source.svg
odoo/addons/l10n_es_aeat_sii_oss/static/description/index.html
odoo/addons/l10n_es_aeat_sii_oss/tests/__init__.py
odoo/addons/l10n_es_aeat_sii_oss/tests/test_l10n_es_aeat_sii.py
odoo13_addon_l10n_es_aeat_sii_oss-13.0.1.0.1.dev2.dist-info/METADATA
odoo13_addon_l10n_es_aeat_sii_oss-13.0.1.0.1.dev2.dist-info/WHEEL
odoo13_addon_l10n_es_aeat_sii_oss-13.0.1.0.1.dev2.dist-info/top_level.txt
odoo13_addon_l10n_es_aeat_sii_oss-13.0.1.0.1.dev2.dist-info/RECORD
